sphinx_mindmap/__init__.py
sphinx_mindmap/_static/jquery/LICENSE.txt
sphinx_mindmap/_static/jquery/jquery-3.7.1.min
sphinx_mindmap/_static/mindmap.html
sphinx_mindmap/_static/vis-network/LICENSE-APACHE-2.0
sphinx_mindmap/_static/vis-network/LICENSE-MIT
sphinx_mindmap/_static/vis-network/package.json
sphinx_mindmap/_static/vis-network/vis-network.min.js
sphinx_mindmap/_static/vis-network/vis-network.min.js.map
sphinx_mindmap-0.5.2.dist-info/LICENSE
sphinx_mindmap-0.5.2.dist-info/METADATA
sphinx_mindmap-0.5.2.dist-info/WHEEL
sphinx_mindmap-0.5.2.dist-info/RECORD
