Metadata-Version: 2.1
Name: sphinx_mindmap
Version: 0.5.2
Summary: Visualization of Mindmap represented in plantuml format using visjs network
Home-page: https://github.com/mi-parkes/sphinx_mindmap
License: MIT
Author: Michael Parkes
Author-email: mparkes@post.cz
Requires-Python: >=3.10,<4.0
Classifier: License :: OSI Approved :: MIT License
Classifier: Programming Language :: Python :: 3
Classifier: Programming Language :: Python :: 3.10
Classifier: Programming Language :: Python :: 3.11
Classifier: Programming Language :: Python :: 3.12
Requires-Dist: Sphinx (>=6.1.3)
Project-URL: Documentation, https://mi-parkes.github.io/sphinx_mindmap/
Project-URL: Repository, https://github.com/mi-parkes/sphinx_mindmap
